chinchilla/__init__.py
chinchilla/_logger.py
chinchilla/_metrics.py
chinchilla/_utils.py
chinchilla/_validator.py
chinchilla/core.py
chinchilla/database.py
chinchilla/simulator.py
chinchilla/visualizer.py
chinchilla-0.2.0.dist-info/LICENSE
chinchilla-0.2.0.dist-info/METADATA
chinchilla-0.2.0.dist-info/WHEEL
chinchilla-0.2.0.dist-info/top_level.txt
chinchilla-0.2.0.dist-info/RECORD
