Metadata-Version: 2.2
Name: chinchilla
Version: 0.2.0
Summary: A toolkit for scaling law research
Author-email: Kyo Takano <kyo.takano@mentalese.co>
License: 
Project-URL: Homepage, https://github.com/kyo-takano/chinchilla
Classifier: Programming Language :: Python
Classifier: Programming Language :: Python :: 3
Classifier: Programming Language :: Python :: 3 :: Only
Classifier: Programming Language :: Python :: 3.8
Classifier: Programming Language :: Python :: 3.9
Classifier: Programming Language :: Python :: 3.10
Classifier: Programming Language :: Python :: 3.11
Classifier: Programming Language :: Python :: 3.12
Classifier: Topic :: Scientific/Engineering
Classifier: License :: OSI Approved :: MIT License
Classifier: Operating System :: OS Independent
Requires-Python: >=3.8
License-File: LICENSE
Requires-Dist: pydantic<3.0.0,>=2.0.0
Requires-Dist: numpy
Requires-Dist: scipy
Requires-Dist: rich
Requires-Dist: seaborn
Requires-Dist: ruamel.yaml>=0.18.0
Requires-Dist: attrdictx
Requires-Dist: ordinal
Provides-Extra: test
Requires-Dist: pytest; extra == "test"
